django_http_exceptions/__init__.py
django_http_exceptions/_exceptions.py
django_http_exceptions/exceptions.py
django_http_exceptions/middleware.py
django_http_exceptions/utils.py
django_http_exceptions-1.4.2.dist-info/LICENSE
django_http_exceptions-1.4.2.dist-info/METADATA
django_http_exceptions-1.4.2.dist-info/WHEEL
django_http_exceptions-1.4.2.dist-info/top_level.txt
django_http_exceptions-1.4.2.dist-info/RECORD
