Metadata-Version: 2.1
Name: django_http_exceptions
Version: 1.4.2
Summary: Django raisable HTTP exceptions
Author-email: isik-kaplan <isik.kaplan.social@outlook.com>
License: MIT LICENSE
Project-URL: Homepage, https://github.com/isik-kaplan/django_http_exceptions
Classifier: License :: OSI Approved :: MIT License
Classifier: Programming Language :: Python :: 3
Classifier: Framework :: Django
Classifier: Development Status :: 5 - Production/Stable
Requires-Python: >=3.5
License-File: LICENSE
Requires-Dist: django>=2.0
